wwpdb/utils/ws_utils/NOTES.SAVE
wwpdb/utils/ws_utils/ServiceDataStore.py
wwpdb/utils/ws_utils/ServiceHistory.py
wwpdb/utils/ws_utils/ServiceLockFile.py
wwpdb/utils/ws_utils/ServiceRequest.py
wwpdb/utils/ws_utils/ServiceResponse.py
wwpdb/utils/ws_utils/ServiceSessionFactory.py
wwpdb/utils/ws_utils/ServiceSessionState.py
wwpdb/utils/ws_utils/ServiceSmtpUtils.py
wwpdb/utils/ws_utils/ServiceUploadUtils.py
wwpdb/utils/ws_utils/ServiceUtilsMisc.py
wwpdb/utils/ws_utils/ServiceWorkerBase.py
wwpdb/utils/ws_utils/TokenUtils.py
wwpdb/utils/ws_utils/__init__.py
wwpdb_utils_ws_utils-0.7.dist-info/METADATA
wwpdb_utils_ws_utils-0.7.dist-info/WHEEL
wwpdb_utils_ws_utils-0.7.dist-info/RECORD
