Metadata-Version: 2.4
Name: wwpdb.utils.ws-utils
Version: 0.7
Summary: wwPDB remote services support library
Project-URL: Homepage, https://github.com/rcsb/py-wwpdb_utils_ws_utils
Author-email: Ezra Peisach <ezra.peisach@rcsb.org>
License-Expression: Apache-2.0
Classifier: Development Status :: 3 - Alpha
Classifier: Intended Audience :: Developers
Classifier: License :: OSI Approved :: Apache Software License
Classifier: Natural Language :: English
Classifier: Programming Language :: Python
Classifier: Programming Language :: Python :: 3
Classifier: Programming Language :: Python :: 3.6
Classifier: Programming Language :: Python :: 3.7
Requires-Python: >=3.8
Requires-Dist: oslo-concurrency
Requires-Dist: pyjwt
Requires-Dist: python-dateutil
Requires-Dist: webob
Requires-Dist: wwpdb-utils-config
